biosppy/__init__.py
biosppy/__version__.py
biosppy/biometrics.py
biosppy/clustering.py
biosppy/metrics.py
biosppy/plotting.py
biosppy/quality.py
biosppy/stats.py
biosppy/storage.py
biosppy/timing.py
biosppy/utils.py
biosppy/features/__init__.py
biosppy/features/cepstral.py
biosppy/features/frequency.py
biosppy/features/phase_space.py
biosppy/features/time.py
biosppy/features/time_freq.py
biosppy/inter_plotting/__init__.py
biosppy/inter_plotting/acc.py
biosppy/inter_plotting/ecg.py
biosppy/signals/__init__.py
biosppy/signals/abp.py
biosppy/signals/acc.py
biosppy/signals/bvp.py
biosppy/signals/ecg.py
biosppy/signals/eda.py
biosppy/signals/eeg.py
biosppy/signals/emg.py
biosppy/signals/hrv.py
biosppy/signals/pcg.py
biosppy/signals/ppg.py
biosppy/signals/resp.py
biosppy/signals/tools.py
biosppy/synthesizers/__init__.py
biosppy/synthesizers/ecg.py
biosppy/synthesizers/emg.py
biosppy-2.2.2.dist-info/AUTHORS.md
biosppy-2.2.2.dist-info/LICENSE
biosppy-2.2.2.dist-info/METADATA
biosppy-2.2.2.dist-info/WHEEL
biosppy-2.2.2.dist-info/top_level.txt
biosppy-2.2.2.dist-info/RECORD
