Metadata-Version: 2.1
Name: biosppy
Version: 2.2.2
Summary: A toolbox for biosignal processing written in Python.
Home-page: https://github.com/scientisst/BioSPPy
Author: Instituto de Telecomunicacoes
Author-email: developer@scientisst.com
License: BSD 3-clause
Classifier: Intended Audience :: Developers
Classifier: Intended Audience :: Education
Classifier: Intended Audience :: Science/Research
Classifier: Natural Language :: English
Classifier: License :: OSI Approved :: BSD License
Classifier: Programming Language :: Python
Classifier: Programming Language :: Python :: 3
Classifier: Programming Language :: Python :: 3.5
Classifier: Programming Language :: Python :: 3.6
Classifier: Programming Language :: Python :: Implementation :: CPython
Classifier: Programming Language :: Python :: Implementation :: PyPy
Classifier: Operating System :: OS Independent
Requires-Python: >3.5.2
License-File: LICENSE
License-File: AUTHORS.md
Requires-Dist: bidict
Requires-Dist: h5py
Requires-Dist: matplotlib
Requires-Dist: numpy
Requires-Dist: scikit-learn
Requires-Dist: scipy
Requires-Dist: shortuuid
Requires-Dist: six
Requires-Dist: joblib
Requires-Dist: opencv-python
Requires-Dist: pywavelets
Requires-Dist: mock
Provides-Extra: eda
Requires-Dist: cvxopt ; extra == 'eda'
